simplify/__init__.py
simplify/_version.py
simplify/benchmark.py
simplify/configuration.py
simplify/exceptions.py
simplify/fitter.py
simplify/model_tools.py
simplify/plot.py
simplify/simplified.py
simplify/yields.py
simplify/cli/__init__.py
simplify/helpers/__init__.py
simplify/helpers/plotting.py
simplify-0.1.10.dist-info/LICENSE
simplify-0.1.10.dist-info/METADATA
simplify-0.1.10.dist-info/WHEEL
simplify-0.1.10.dist-info/entry_points.txt
simplify-0.1.10.dist-info/top_level.txt
simplify-0.1.10.dist-info/RECORD
