Metadata-Version: 2.1
Name: simplify
Version: 0.1.10
Summary: Produce simplified likelihoods of different formats
Home-page: UNKNOWN
Author: Eric Schanet
License: BSD 3-Clause
Project-URL: Source, https://github.com/eschanet/simplify
Project-URL: Tracker, https://github.com/eschanet/simplify/issues
Platform: UNKNOWN
Classifier: Development Status :: 3 - Alpha
Classifier: Programming Language :: Python :: 3
Classifier: Programming Language :: Python :: 3 :: Only
Classifier: Programming Language :: Python :: 3.7
Classifier: Programming Language :: Python :: 3.8
Classifier: Programming Language :: Python :: 3.9
Classifier: Programming Language :: Python :: Implementation :: CPython
Classifier: License :: OSI Approved :: BSD License
Classifier: Topic :: Scientific/Engineering
Classifier: Topic :: Scientific/Engineering :: Physics
Classifier: Intended Audience :: Science/Research
Requires-Python: >=3.7
Provides-Extra: contrib
Provides-Extra: test
Provides-Extra: develop
Provides-Extra: complete
License-File: LICENSE
